Workbook
Name Aporte: Ferramenta!$D$14:$D$14
Name Dividendos: Ferramenta!$D$18:$D$18
Name Patrimonio_Acumulado: Ferramenta!$D$17:$D$17
Name Rendimento_Carteira: Ferramenta!$D$10:$D$10
Name Salario: Ferramenta!$D$9:$D$9
Name Taxa_Mensal: Ferramenta!$D$16:$D$16
Name Tempo_Investido: Ferramenta!$D$15:$D$15

Sheet Ferramenta
B8: CONFIGURAÇÕES
B9: Salário | D9: 5000
B10: Rendimento Carteira | D10: 0.0089
B11: Sugestão de Investimento | D11: {=Salario*30%} -> 1500
B13: INVESTIMENTO MENSAL
A14: 2 | B14: Quanto Investir por mês? | D14: 750
A15: 5 | B15: Por quantos anos? | D15: 5
A16: 10 | B16: Taxa de rendimento mensal? | D16: 0.01079
A17: 20 | B17: Patrimônio acumulado | D17: {=FV(Taxa_Mensal,Tempo_Investido*12,Aporte*-1)} -> 62832.685
A18: 30 | B18: Dividendos mensais | D18: =D17*D16 -> 677.96468
B20: Cenários | C20: Patrimônio | D20: Dividendo
B21: Quanto terei em 2 anos? | C21: =FV($D$16,A14*12,$D$14*-1) -> 20420.72 | D21: =C21*$D$10 -> 181.74441
B22: Quanto terei em 5 anos? | C22: =FV($D$16,A15*12,$D$14*-1) -> 62832.685 | D22: =C22*$D$10 -> 559.2109
B23: Quanto terei em 10 anos? | C23: =FV($D$16,A16*12,$D$14*-1) -> 182463.16 | D23: =C23*$D$10 -> 1623.9221
B24: Quanto terei em 20 anos? | C24: =FV($D$16,A17*12,$D$14*-1) -> 843898.8 | D24: =C24*$D$10 -> 7510.6993
B25: Quanto terei em 30 anos? | C25: =FV($D$16,A18*12,$D$14*-1) -> 3241627.2 | D25: =C25*$D$10 -> 28850.482
B27: PERFIL | C27: Conservador
B28: Valor a ser investido por mês | C28: 500
B30: TIPO DE FII | C30: PERCENTUAL SUGERIDO | D30: VALORES
B31: Papel | C31: =VLOOKUP($C$27&"-"&B31,Apoio!A3:D21,4,FALSE) -> 0.3 | D31: =C31*$C$28 -> 150
B32: Tijolo | C32: =VLOOKUP($C$27&"-"&B32,Apoio!A4:D22,4,FALSE) -> 0.5 | D32: =C32*$C$28 -> 250
B33: Híbrido | C33: =VLOOKUP($C$27&"-"&B33,Apoio!A5:D23,4,FALSE) -> 0.1 | D33: =C33*$C$28 -> 50
B34: FOFs | C34: =VLOOKUP($C$27&"-"&B34,Apoio!A6:D24,4,FALSE) -> 0.1 | D34: =C34*$C$28 -> 50
B35: Desenvolvimento | C35: =VLOOKUP($C$27&"-"&B35,Apoio!A7:D25,4,FALSE) -> 0 | D35: =C35*$C$28 -> 0
B36: Hotelaria | C36: =VLOOKUP($C$27&"-"&B36,Apoio!A8:D26,4,FALSE) -> 0 | D36: =C36*$C$28 -> 0

Sheet Apoio
A3: CHAVE | B3: PERFIL | C3: TIPO DE FII | D3: %
A4: =B4&"-"&C4 -> Conservador-Papel | B4: Conservador | C4: Papel | D4: 0.3
A5: =B5&"-"&C5 -> Conservador-Tijolo | B5: Conservador | C5: Tijolo | D5: 0.5
A6: =B6&"-"&C6 -> Conservador-Híbrido | B6: Conservador | C6: Híbrido | D6: 0.1
A7: =B7&"-"&C7 -> Conservador-FOFs | B7: Conservador | C7: FOFs | D7: 0.1
A8: =B8&"-"&C8 -> Conservador-Desenvolvimento | B8: Conservador | C8: Desenvolvimento | D8: 0
A9: =B9&"-"&C9 -> Conservador-Hotelaria | B9: Conservador | C9: Hotelaria | D9: 0
A10: =B10&"-"&C10 -> Moderado-Papel | B10: Moderado | C10: Papel | D10: 0.32
A11: =B11&"-"&C11 -> Moderado-Tijolo | B11: Moderado | C11: Tijolo | D11: 0.35
A12: =B12&"-"&C12 -> Moderado-Híbrido | B12: Moderado | C12: Híbrido | D12: 0.08
A13: =B13&"-"&C13 -> Moderado-FOFs | B13: Moderado | C13: FOFs | D13: 0.05
A14: =B14&"-"&C14 -> Moderado-Desenvolvimento | B14: Moderado | C14: Desenvolvimento | D14: 0.1
A15: =B15&"-"&C15 -> Moderado-Hotelaria | B15: Moderado | C15: Hotelaria | D15: 0.1
... A21: =B21&"-"&C21 -> Arrojado-Hotelaria | B21: Arrojado | C21: Hotelaria | D21: 0.1
